{
  "illusts": [
    {
      "caption": "雪miku2号入围作品应援！",
      "create_date": "2018-06-26T01:09:56+09:00",
      "height": 1500,
      "id": 69406848,
      "image_urls": {
        "large": "https://i.pximg.net/c/600x1200_90/img-master/img/2018/06/26/01/09/56/69406848_p0_master1200.jpg",
        "medium": "https://i.pximg.net/c/540x540_70/img-master/img/2018/06/26/01/09/56/69406848_p0_master1200.jpg",
        "square_medium": "https://i.pximg.net/c/360x360_70/img-master/img/2018/06/26/01/09/56/69406848_p0_square1200.jpg"
      },
      "is_bookmarked": false,
      "is_muted": false,
      "meta_pages": [
        {
          "image_urls": {
            "large": "https://i.pximg.net/c/600x1200_90/img-master/img/2018/06/26/01/09/56/69406848_p0_master1200.jpg",
            "medium": "https://i.pximg.net/c/540x540_70/img-master/img/2018/06/26/01/09/56/69406848_p0_master1200.jpg",
            "original": "https://i.pximg.net/img-original/img/2018/06/26/01/09/56/69406848_p0.jpg",
            "square_medium": "https://i.pximg.net/c/360x360_70/img-master/img/2018/06/26/01/09/56/69406848_p0_square1200.jpg"
          }
        },
        {
          "image_urls": {
            "large": "https://i.pximg.net/c/600x1200_90/img-master/img/2018/06/26/01/09/56/69406848_p1_master1200.jpg",
            "medium": "https://i.pximg.net/c/540x540_70/img-master/img/2018/06/26/01/09/56/69406848_p1_master1200.jpg",
            "original": "https://i.pximg.net/img-original/img/2018/06/26/01/09/56/69406848_p1.jpg",
            "square_medium": "https://i.pximg.net/c/360x360_70/img-master/img/2018/06/26/01/09/56/69406848_p1_square1200.jpg"
          }
        },
        {
          "image_urls": {
            "large": "https://i.pximg.net/c/600x1200_90/img-master/img/2018/06/26/01/09/56/69406848_p2_master1200.jpg",
            "medium": "https://i.pximg.net/c/540x540_70/img-master/img/2018/06/26/01/09/56/69406848_p2_master1200.jpg",
            "original": "https://i.pximg.net/img-original/img/2018/06/26/01/09/56/69406848_p2.jpg",
            "square_medium": "https://i.pximg.net/c/360x360_70/img-master/img/2018/06/26/01/09/56/69406848_p2_square1200.jpg"
          }
        }
      ],
      "meta_single_page": {},
      "page_count": 3,
      "restrict": 0,
      "sanity_level": 2,
      "series": null,
      "tags": [
        {
          "name": "初音ミク",
          "translated_name": null
        },
        {
          "name": "VOCALOID",
          "translated_name": null
        },
        {
          "name": "雪ミク衣装",
          "translated_name": null
        },
        {
          "name": "雪ミク",
          "translated_name": null
        },
        {
          "name": "雪初音",
          "translated_name": null
        },
        {
          "name": "2019年雪ミク衣装",
          "translated_name": null
        },
        {
          "name": "雪ミク2019",
          "translated_name": null
        },
        {
          "name": "VOCALOID5000users",
          "translated_name": null
        },
        {
          "name": "VOCALOID5000users入り",
          "translated_name": null
        }
      ],
      "title": "雪ミク",
      "tools": [],
      "total_bookmarks": 7023,
      "total_view": 36975,
      "type": "illust",
      "user": {
        "account": "yy58531214",
        "id": 8890590,
        "is_followed": false,
        "name": "瑛",
        "profile_image_urls": {
          "medium": "https://i.pximg.net/user-profile/img/2014/11/01/17/53/49/8573541_79859d932b4b39258a8c89906ae6d266_170.jpg"
        }
      },
      "visible": true,
      "width": 1500,
      "x_restrict": 0
    },
    {
      "caption": "",
      "create_date": "2018-12-13T00:00:08+09:00",
      "height": 3577,
      "id": 72086224,
      "image_urls": {
        "large": "https://i.pximg.net/c/600x1200_90/img-master/img/2018/12/13/00/55/10/72086224_p0_master1200.jpg",
        "medium": "https://i.pximg.net/c/540x540_70/img-master/img/2018/12/13/00/55/10/72086224_p0_master1200.jpg",
        "square_medium": "https://i.pximg.net/c/360x360_70/img-master/img/2018/12/13/00/55/10/72086224_p0_square1200.jpg"
      },
      "is_bookmarked": false,
      "is_muted": false,
      "meta_pages": [],
      "meta_single_page": {
        "original_image_url": "https://i.pximg.net/img-original/img/2018/12/13/00/55/10/72086224_p0.png"
      },
      "page_count": 1,
      "restrict": 0,
      "sanity_level": 2,
      "series": null,
      "tags": [
        {
          "name": "少女",
          "translated_name": null
        },
        {
          "name": "VOCALOID",
          "translated_name": null
        },
        {
          "name": "初音ミク",
          "translated_name": null
        },
        {
          "name": "雪ミク",
          "translated_name": null
        },
        {
          "name": "雪ミク2019",
          "translated_name": null
        },
        {
          "name": "VOCALOID1000users入り",
          "translated_name": null
        }
      ],
      "title": "SNOWMIKU",
      "tools": [
        "CLIP STUDIO PAINT",
        "筆"
      ],
      "total_bookmarks": 4564,
      "total_view": 23195,
      "type": "illust",
      "user": {
        "account": "user_mwwe3558",
        "id": 23098486,
        "is_followed": false,
        "name": "TOKKYU",
        "profile_image_urls": {
          "medium": "https://i.pximg.net/user-profile/img/2019/04/18/13/03/03/15662042_10f8d3c70c44d70748bbdf303e2e79e9_170.jpg"
        }
      },
      "visible": true,
      "width": 3000,
      "x_restrict": 0
    },
    {
      "caption": "❄️雪ミク❄️を描くのはいつも楽しい。 :)<br />上のイラストに関連する映像はこちらから <br /><a href=\"https://www.youtube.com/watch?v=seOlKtSHIr0\" target=\"_blank\">https://www.youtube.com/watch?v=seOlKtSHIr0</a><br />❄️❄️❄️❄️❄️❄️❄️❄️❄️❄️❄️❄️❄️❄️❄️❄️❄️❄️❄️❄️❄️❄️❄️❄️❄️❄️❄️❄️❄️",
      "create_date": "2019-02-08T00:05:11+09:00",
      "height": 1400,
      "id": 73058617,
      "image_urls": {
        "large": "https://i.pximg.net/c/600x1200_90/img-master/img/2019/02/08/00/05/11/73058617_p0_master1200.jpg",
        "medium": "https://i.pximg.net/c/540x540_70/img-master/img/2019/02/08/00/05/11/73058617_p0_master1200.jpg",
        "square_medium": "https://i.pximg.net/c/360x360_70/img-master/img/2019/02/08/00/05/11/73058617_p0_square1200.jpg"
      },
      "is_bookmarked": false,
      "is_muted": false,
      "meta_pages": [
        {
          "image_urls": {
            "large": "https://i.pximg.net/c/600x1200_90/img-master/img/2019/02/08/00/05/11/73058617_p0_master1200.jpg",
            "medium": "https://i.pximg.net/c/540x540_70/img-master/img/2019/02/08/00/05/11/73058617_p0_master1200.jpg",
            "original": "https://i.pximg.net/img-original/img/2019/02/08/00/05/11/73058617_p0.jpg",
            "square_medium": "https://i.pximg.net/c/360x360_70/img-master/img/2019/02/08/00/05/11/73058617_p0_square1200.jpg"
          }
        },
        {
          "image_urls": {
            "large": "https://i.pximg.net/c/600x1200_90/img-master/img/2019/02/08/00/05/11/73058617_p1_master1200.jpg",
            "medium": "https://i.pximg.net/c/540x540_70/img-master/img/2019/02/08/00/05/11/73058617_p1_master1200.jpg",
            "original": "https://i.pximg.net/img-original/img/2019/02/08/00/05/11/73058617_p1.jpg",
            "square_medium": "https://i.pximg.net/c/360x360_70/img-master/img/2019/02/08/00/05/11/73058617_p1_square1200.jpg"
          }
        }
      ],
      "meta_single_page": {},
      "page_count": 2,
      "restrict": 0,
      "sanity_level": 2,
      "series": null,
      "tags": [
        {
          "name": "vocaloid",
          "translated_name": null
        },
        {
          "name": "雪ミク2019",
          "translated_name": null
        },
        {
          "name": "雪ミク",
          "translated_name": null
        },
        {
          "name": "初音ミク",
          "translated_name": null
        },
        {
          "name": "miku",
          "translated_name": null
        },
        {
          "name": "VOCALOID1000users入り",
          "translated_name": null
        }
      ],
      "title": "❄️❄️❄️雪ミク♥2019❄️❄️❄️",
      "tools": [
        "Photoshop",
        "鉛筆"
      ],
      "total_bookmarks": 3727,
      "total_view": 29784,
      "type": "illust",
      "user": {
        "account": "kkuem",
        "id": 45438,
        "is_followed": false,
        "name": "KKUEMㆍクエム",
        "profile_image_urls": {
          "medium": "https://i.pximg.net/user-profile/img/2013/06/06/01/02/29/6332423_404e065e5f4f6ea9e8336812516ac522_170.jpg"
        }
      },
      "visible": true,
      "width": 1095,
      "x_restrict": 0
    },
    {
      "caption": "「SNOW MIKU 2019」のサブビジュアルを描かせて頂きました。<br />プリンセスのお茶会をイメージして描きました！<br />キラキラとした衣装デザインが素敵で楽しかったです。<br /><br />特設サイト：<a href=\"https://snowmiku.com/2019/\" target=\"_blank\">https://snowmiku.com/2019/</a>",
      "create_date": "2018-12-13T00:53:31+09:00",
      "height": 900,
      "id": 72087309,
      "image_urls": {
        "large": "https://i.pximg.net/c/600x1200_90/img-master/img/2018/12/13/00/53/31/72087309_p0_master1200.jpg",
        "medium": "https://i.pximg.net/c/540x540_70/img-master/img/2018/12/13/00/53/31/72087309_p0_master1200.jpg",
        "square_medium": "https://i.pximg.net/c/360x360_70/img-master/img/2018/12/13/00/53/31/72087309_p0_square1200.jpg"
      },
      "is_bookmarked": false,
      "is_muted": false,
      "meta_pages": [],
      "meta_single_page": {
        "original_image_url": "https://i.pximg.net/img-original/img/2018/12/13/00/53/31/72087309_p0.jpg"
      },
      "page_count": 1,
      "restrict": 0,
      "sanity_level": 2,
      "series": null,
      "tags": [
        {
          "name": "雪ミク",
          "translated_name": null
        },
        {
          "name": "初音ミク",
          "translated_name": null
        },
        {
          "name": "VOCALOID",
          "translated_name": null
        },
        {
          "name": "雪ミク2019",
          "translated_name": null
        },
        {
          "name": "VOCALOID5000users入り",
          "translated_name": null
        }
      ],
      "title": "SNOW MIKU 2019",
      "tools": [],
      "total_bookmarks": 8591,
      "total_view": 55297,
      "type": "illust",
      "user": {
        "account": "uekuraeku",
        "id": 299299,
        "is_followed": false,
        "name": "上倉エク",
        "profile_image_urls": {
          "medium": "https://i.pximg.net/user-profile/img/2019/01/01/14/23/00/15200316_554d50678fdf55f02aff9899e1daec9b_170.png"
        }
      },
      "visible": true,
      "width": 640,
      "x_restrict": 0
    },
    {
      "caption": "我……我还活着……年……年更……",
      "create_date": "2018-12-09T17:00:11+09:00",
      "height": 1214,
      "id": 72036945,
      "image_urls": {
        "large": "https://i.pximg.net/c/600x1200_90/img-master/img/2018/12/09/17/00/11/72036945_p0_master1200.jpg",
        "medium": "https://i.pximg.net/c/540x540_70/img-master/img/2018/12/09/17/00/11/72036945_p0_master1200.jpg",
        "square_medium": "https://i.pximg.net/c/360x360_70/img-master/img/2018/12/09/17/00/11/72036945_p0_square1200.jpg"
      },
      "is_bookmarked": false,
      "is_muted": false,
      "meta_pages": [],
      "meta_single_page": {
        "original_image_url": "https://i.pximg.net/img-original/img/2018/12/09/17/00/11/72036945_p0.jpg"
      },
      "page_count": 1,
      "restrict": 0,
      "sanity_level": 2,
      "series": null,
      "tags": [
        {
          "name": "VOCALOID",
          "translated_name": null
        },
        {
          "name": "初音ミク",
          "translated_name": null
        },
        {
          "name": "雪ミク2019",
          "translated_name": null
        },
        {
          "name": "雪ミク",
          "translated_name": null
        },
        {
          "name": "VOCALOID1000users入り",
          "translated_name": null
        }
      ],
      "title": "雪ミク2019",
      "tools": [
        "SAI"
      ],
      "total_bookmarks": 2431,
      "total_view": 14433,
      "type": "illust",
      "user": {
        "account": "jinko0094",
        "id": 3693527,
        "is_followed": false,
        "name": "Jinko_神子",
        "profile_image_urls": {
          "medium": "https://i.pximg.net/user-profile/img/2016/01/24/23/25/39/10429912_b611414ab913a6cb576f94ed23aae0fa_170.jpg"
        }
      },
      "visible": true,
      "width": 850,
      "x_restrict": 0
    },
    {
      "caption": "",
      "create_date": "2018-08-29T16:00:00+09:00",
      "height": 914,
      "id": 70441067,
      "image_urls": {
        "large": "https://i.pximg.net/c/600x1200_90/img-master/img/2018/08/29/16/00/00/70441067_p0_master1200.jpg",
        "medium": "https://i.pximg.net/c/540x540_70/img-master/img/2018/08/29/16/00/00/70441067_p0_master1200.jpg",
        "square_medium": "https://i.pximg.net/c/360x360_70/img-master/img/2018/08/29/16/00/00/70441067_p0_square1200.jpg"
      },
      "is_bookmarked": false,
      "is_muted": false,
      "meta_pages": [],
      "meta_single_page": {
        "original_image_url": "https://i.pximg.net/img-original/img/2018/08/29/16/00/00/70441067_p0.png"
      },
      "page_count": 1,
      "restrict": 0,
      "sanity_level": 2,
      "series": null,
      "tags": [
        {
          "name": "VOCALOID",
          "translated_name": null
        },
        {
          "name": "初音ミク",
          "translated_name": null
        },
        {
          "name": "はいてない",
          "translated_name": null
        },
        {
          "name": "魅惑のふともも",
          "translated_name": null
        },
        {
          "name": "VOCALOID10000users入り",
          "translated_name": null
        },
        {
          "name": "誕生日おめでとう",
          "translated_name": null
        },
        {
          "name": "初音ミク生誕祭2018",
          "translated_name": null
        }
      ],
      "title": "♡",
      "tools": [
        "CLIP STUDIO PAINT"
      ],
      "total_bookmarks": 20325,
      "total_view": 132223,
      "type": "illust",
      "user": {
        "account": "lpmya",
        "id": 6996493,
        "is_followed": false,
        "name": "Lpip",
        "profile_image_urls": {
          "medium": "https://i.pximg.net/user-profile/img/2019/05/06/03/12/24/15734998_67be635a51cdf6701446f93e8fa517ff_170.png"
        }
      },
      "visible": true,
      "width": 650,
      "x_restrict": 0
    },
    {
      "caption": "明日から店舗、オンラインにて展開されるプライズ用フィギュアのイラストを描かせていただきました。<br />どうぞ、よろしくお願いいたします！<br /><br />詳細：<a href=\"https://www.taito.co.jp/miku\" target=\"_blank\">https://www.taito.co.jp/miku</a>",
      "create_date": "2019-02-26T20:02:12+09:00",
      "height": 2032,
      "id": 73404075,
      "image_urls": {
        "large": "https://i.pximg.net/c/600x1200_90/img-master/img/2019/02/26/20/02/12/73404075_p0_master1200.jpg",
        "medium": "https://i.pximg.net/c/540x540_70/img-master/img/2019/02/26/20/02/12/73404075_p0_master1200.jpg",
        "square_medium": "https://i.pximg.net/c/360x360_70/img-master/img/2019/02/26/20/02/12/73404075_p0_square1200.jpg"
      },
      "is_bookmarked": false,
      "is_muted": false,
      "meta_pages": [],
      "meta_single_page": {
        "original_image_url": "https://i.pximg.net/img-original/img/2019/02/26/20/02/12/73404075_p0.png"
      },
      "page_count": 1,
      "restrict": 0,
      "sanity_level": 2,
      "series": null,
      "tags": [
        {
          "name": "VOCALOID",
          "translated_name": null
        },
        {
          "name": "桜ミク",
          "translated_name": null
        },
        {
          "name": "初音ミク",
          "translated_name": null
        },
        {
          "name": "VOCALOID1000users入り",
          "translated_name": null
        }
      ],
      "title": "桜ミク",
      "tools": [],
      "total_bookmarks": 4187,
      "total_view": 31457,
      "type": "illust",
      "user": {
        "account": "munemiu",
        "id": 337971,
        "is_followed": false,
        "name": "U35(うみこ)",
        "profile_image_urls": {
          "medium": "https://i.pximg.net/user-profile/img/2016/07/28/22/24/45/11263313_1bd6349eda7a44f52d0f0f0dc4e2a72d_170.jpg"
        }
      },
      "visible": true,
      "width": 1703,
      "x_restrict": 0
    },
    {
      "caption": "遅刻してごめんなさい！<br />ミクさん大好き！！！",
      "create_date": "2018-09-12T00:00:06+09:00",
      "height": 1004,
      "id": 70653103,
      "image_urls": {
        "large": "https://i.pximg.net/c/600x1200_90/img-master/img/2018/09/12/00/00/06/70653103_p0_master1200.jpg",
        "medium": "https://i.pximg.net/c/540x540_70/img-master/img/2018/09/12/00/00/06/70653103_p0_master1200.jpg",
        "square_medium": "https://i.pximg.net/c/360x360_70/img-master/img/2018/09/12/00/00/06/70653103_p0_square1200.jpg"
      },
      "is_bookmarked": false,
      "is_muted": false,
      "meta_pages": [],
      "meta_single_page": {
        "original_image_url": "https://i.pximg.net/img-original/img/2018/09/12/00/00/06/70653103_p0.jpg"
      },
      "page_count": 1,
      "restrict": 0,
      "sanity_level": 2,
      "series": null,
      "tags": [
        {
          "name": "初音ミク",
          "translated_name": null
        },
        {
          "name": "初音ミク生誕祭2018",
          "translated_name": null
        },
        {
          "name": "雪ミク",
          "translated_name": null
        },
        {
          "name": "雪ミク2019",
          "translated_name": null
        },
        {
          "name": "VOCALOID",
          "translated_name": null
        },
        {
          "name": "VOCALOID10000users入り",
          "translated_name": null
        }
      ],
      "title": "ミクさんHappy Birthday",
      "tools": [
        "Photoshop"
      ],
      "total_bookmarks": 11473,
      "total_view": 55455,
      "type": "illust",
      "user": {
        "account": "korokoroudon",
        "id": 2458,
        "is_followed": false,
        "name": "ののこ",
        "profile_image_urls": {
          "medium": "https://i.pximg.net/user-profile/img/2019/01/02/10/41/30/15204350_d47b67f2e57df1911d0a1a848e4a2767_170.jpg"
        }
      },
      "visible": true,
      "width": 950,
      "x_restrict": 0
    },
    {
      "caption": "みくのひ！",
      "create_date": "2019-03-09T19:15:19+09:00",
      "height": 930,
      "id": 73591526,
      "image_urls": {
        "large": "https://i.pximg.net/c/600x1200_90/img-master/img/2019/03/09/19/15/19/73591526_p0_master1200.jpg",
        "medium": "https://i.pximg.net/c/540x540_70/img-master/img/2019/03/09/19/15/19/73591526_p0_master1200.jpg",
        "square_medium": "https://i.pximg.net/c/360x360_70/img-master/img/2019/03/09/19/15/19/73591526_p0_square1200.jpg"
      },
      "is_bookmarked": false,
      "is_muted": false,
      "meta_pages": [],
      "meta_single_page": {
        "original_image_url": "https://i.pximg.net/img-original/img/2019/03/09/19/15/19/73591526_p0.jpg"
      },
      "page_count": 1,
      "restrict": 0,
      "sanity_level": 4,
      "series": null,
      "tags": [
        {
          "name": "VOCALOID",
          "translated_name": null
        },
        {
          "name": "初音ミク",
          "translated_name": null
        },
        {
          "name": "マニキュア",
          "translated_name": null
        },
        {
          "name": "VOCALOID1000users入り",
          "translated_name": null
        },
        {
          "name": "ミクの日2019",
          "translated_name": null
        }
      ],
      "title": "39",
      "tools": [
        "SAI"
      ],
      "total_bookmarks": 4224,
      "total_view": 23642,
      "type": "illust",
      "user": {
        "account": "liar-player",
        "id": 1243867,
        "is_followed": false,
        "name": "黎（クロイ）",
        "profile_image_urls": {
          "medium": "https://i.pximg.net/user-profile/img/2017/02/14/22/32/12/12148776_136f0c41cd7d37e1a10bcaf6505ac816_170.png"
        }
      },
      "visible": true,
      "width": 930,
      "x_restrict": 0
    },
    {
      "caption": "たらんさん(<strong><a href=\"pixiv://users/1774094\">user/1774094</a></strong>)の雪ミクデザインに一目惚れしちゃって描きました(*´∀`*)<br />詳しいデザインはこちらです！→ <a href=\"http://piapro.jp/t/RZjR\" target=\"_blank\">http://piapro.jp/t/RZjR</a>",
      "create_date": "2016-05-21T14:50:45+09:00",
      "height": 1200,
      "id": 56985812,
      "image_urls": {
        "large": "https://i.pximg.net/c/600x1200_90/img-master/img/2016/05/21/14/50/45/56985812_p0_master1200.jpg",
        "medium": "https://i.pximg.net/c/540x540_70/img-master/img/2016/05/21/14/50/45/56985812_p0_master1200.jpg",
        "square_medium": "https://i.pximg.net/c/360x360_70/img-master/img/2016/05/21/14/50/45/56985812_p0_square1200.jpg"
      },
      "is_bookmarked": false,
      "is_muted": false,
      "meta_pages": [],
      "meta_single_page": {
        "original_image_url": "https://i.pximg.net/img-original/img/2016/05/21/14/50/45/56985812_p0.jpg"
      },
      "page_count": 1,
      "restrict": 0,
      "sanity_level": 2,
      "series": null,
      "tags": [
        {
          "name": "初音ミク",
          "translated_name": null
        },
        {
          "name": "VOCALOID",
          "translated_name": null
        },
        {
          "name": "雪ミク",
          "translated_name": null
        },
        {
          "name": "ワンピース服",
          "translated_name": null
        },
        {
          "name": "ノースリーブワンピース",
          "translated_name": null
        },
        {
          "name": "VOCALOID10000users入り",
          "translated_name": null
        }
      ],
      "title": "Snow Miku",
      "tools": [
        "CLIP STUDIO PAINT"
      ],
      "total_bookmarks": 25798,
      "total_view": 346139,
      "type": "illust",
      "user": {
        "account": "nardack",
        "id": 341433,
        "is_followed": false,
        "name": "Nardack",
        "profile_image_urls": {
          "medium": "https://i.pximg.net/user-profile/img/2009/06/17/00/14/26/846482_b4865021778259d4bad8a4d359b4870a_170.jpg"
        }
      },
      "visible": true,
      "width": 1426,
      "x_restrict": 0
    },
    {
      "caption": "",
      "create_date": "2018-12-22T00:22:13+09:00",
      "height": 1080,
      "id": 72218158,
      "image_urls": {
        "large": "https://i.pximg.net/c/600x1200_90/img-master/img/2018/12/22/00/22/13/72218158_p0_master1200.jpg",
        "medium": "https://i.pximg.net/c/540x540_70/img-master/img/2018/12/22/00/22/13/72218158_p0_master1200.jpg",
        "square_medium": "https://i.pximg.net/c/360x360_70/img-master/img/2018/12/22/00/22/13/72218158_p0_square1200.jpg"
      },
      "is_bookmarked": false,
      "is_muted": false,
      "meta_pages": [],
      "meta_single_page": {
        "original_image_url": "https://i.pximg.net/img-original/img/2018/12/22/00/22/13/72218158_p0.jpg"
      },
      "page_count": 1,
      "restrict": 0,
      "sanity_level": 2,
      "series": null,
      "tags": [
        {
          "name": "VOCALOID",
          "translated_name": null
        },
        {
          "name": "雪ミク",
          "translated_name": null
        },
        {
          "name": "初音ミク",
          "translated_name": null
        },
        {
          "name": "女の子",
          "translated_name": null
        },
        {
          "name": "2019雪ミク",
          "translated_name": null
        },
        {
          "name": "雪ミク2019",
          "translated_name": null
        },
        {
          "name": "VOCALOID1000users入り",
          "translated_name": null
        }
      ],
      "title": "snow♛",
      "tools": [
        "SAI",
        "Photoshop"
      ],
      "total_bookmarks": 1348,
      "total_view": 6054,
      "type": "illust",
      "user": {
        "account": "1148656184",
        "id": 7616827,
        "is_followed": false,
        "name": "菓子狸Kakami",
        "profile_image_urls": {
          "medium": "https://i.pximg.net/user-profile/img/2017/11/24/16/19/27/13489976_b0e193e7e1596dbf669ccfcc235ab472_170.jpg"
        }
      },
      "visible": true,
      "width": 1848,
      "x_restrict": 0
    },
    {
      "caption": "",
      "create_date": "2019-01-22T00:00:11+09:00",
      "height": 4334,
      "id": 72780213,
      "image_urls": {
        "large": "https://i.pximg.net/c/600x1200_90/img-master/img/2019/01/22/00/00/11/72780213_p0_master1200.jpg",
        "medium": "https://i.pximg.net/c/540x540_70/img-master/img/2019/01/22/00/00/11/72780213_p0_master1200.jpg",
        "square_medium": "https://i.pximg.net/c/360x360_70/img-master/img/2019/01/22/00/00/11/72780213_p0_square1200.jpg"
      },
      "is_bookmarked": false,
      "is_muted": false,
      "meta_pages": [
        {
          "image_urls": {
            "large": "https://i.pximg.net/c/600x1200_90/img-master/img/2019/01/22/00/00/11/72780213_p0_master1200.jpg",
            "medium": "https://i.pximg.net/c/540x540_70/img-master/img/2019/01/22/00/00/11/72780213_p0_master1200.jpg",
            "original": "https://i.pximg.net/img-original/img/2019/01/22/00/00/11/72780213_p0.jpg",
            "square_medium": "https://i.pximg.net/c/360x360_70/img-master/img/2019/01/22/00/00/11/72780213_p0_square1200.jpg"
          }
        },
        {
          "image_urls": {
            "large": "https://i.pximg.net/c/600x1200_90/img-master/img/2019/01/22/00/00/11/72780213_p1_master1200.jpg",
            "medium": "https://i.pximg.net/c/540x540_70/img-master/img/2019/01/22/00/00/11/72780213_p1_master1200.jpg",
            "original": "https://i.pximg.net/img-original/img/2019/01/22/00/00/11/72780213_p1.jpg",
            "square_medium": "https://i.pximg.net/c/360x360_70/img-master/img/2019/01/22/00/00/11/72780213_p1_square1200.jpg"
          }
        }
      ],
      "meta_single_page": {},
      "page_count": 2,
      "restrict": 0,
      "sanity_level": 2,
      "series": null,
      "tags": [
        {
          "name": "VOCALOID",
          "translated_name": null
        },
        {
          "name": "雪ミク",
          "translated_name": null
        },
        {
          "name": "初音ミク",
          "translated_name": null
        },
        {
          "name": "女の子",
          "translated_name": null
        },
        {
          "name": "雪ミク2019",
          "translated_name": null
        },
        {
          "name": "VOCALOID1000users入り",
          "translated_name": null
        }
      ],
      "title": "SNOW MIKU 2019",
      "tools": [
        "CLIP STUDIO PAINT"
      ],
      "total_bookmarks": 2107,
      "total_view": 9672,
      "type": "illust",
      "user": {
        "account": "user_rsuf7733",
        "id": 21779378,
        "is_followed": false,
        "name": "foreign blue",
        "profile_image_urls": {
          "medium": "https://i.pximg.net/user-profile/img/2017/10/18/20/56/37/13356795_ea0fbc39b23a2361be50d7c0c7c33a14_170.jpg"
        }
      },
      "visible": true,
      "width": 3000,
      "x_restrict": 0
    },
    {
      "caption": ":.｡..｡.:*･&#39;❉&#39;･*:.｡. .｡.:<br />我开了个Lofter~！<a href=\"http://bisonbison.lofter.com\" target=\"_blank\">http://bisonbison.lofter.com</a>",
      "create_date": "2017-10-23T22:04:18+09:00",
      "height": 1080,
      "id": 65567135,
      "image_urls": {
        "large": "https://i.pximg.net/c/600x1200_90/img-master/img/2017/10/23/22/04/18/65567135_p0_master1200.jpg",
        "medium": "https://i.pximg.net/c/540x540_70/img-master/img/2017/10/23/22/04/18/65567135_p0_master1200.jpg",
        "square_medium": "https://i.pximg.net/c/360x360_70/img-master/img/2017/10/23/22/04/18/65567135_p0_square1200.jpg"
      },
      "is_bookmarked": false,
      "is_muted": false,
      "meta_pages": [],
      "meta_single_page": {
        "original_image_url": "https://i.pximg.net/img-original/img/2017/10/23/22/04/18/65567135_p0.jpg"
      },
      "page_count": 1,
      "restrict": 0,
      "sanity_level": 2,
      "series": null,
      "tags": [
        {
          "name": "初音ミク",
          "translated_name": null
        },
        {
          "name": "雪ミク2018",
          "translated_name": null
        },
        {
          "name": "VOCALOID",
          "translated_name": null
        },
        {
          "name": "雪ミク",
          "translated_name": null
        },
        {
          "name": "VOCALOID10000users入り",
          "translated_name": null
        }
      ],
      "title": "雪月",
      "tools": [
        "SAI",
        "Photoshop"
      ],
      "total_bookmarks": 18066,
      "total_view": 100900,
      "type": "illust",
      "user": {
        "account": "bisonbison",
        "id": 333556,
        "is_followed": false,
        "name": "Bison倉鼠",
        "profile_image_urls": {
          "medium": "https://i.pximg.net/user-profile/img/2017/07/02/01/05/12/12789568_3c23f6a7ddf85061253c2010b49aa6a9_170.jpg"
        }
      },
      "visible": true,
      "width": 1920,
      "x_restrict": 0
    },
    {
      "caption": "<a href=\"https://twitter.com/Sina_S2_/status/1075369186262540288\" target=\"_blank\">https://twitter.com/Sina_S2_/status/1075369186262540288</a>",
      "create_date": "2018-12-20T00:08:22+09:00",
      "height": 919,
      "id": 72189858,
      "image_urls": {
        "large": "https://i.pximg.net/c/600x1200_90/img-master/img/2018/12/20/00/08/22/72189858_p0_master1200.jpg",
        "medium": "https://i.pximg.net/c/540x540_70/img-master/img/2018/12/20/00/08/22/72189858_p0_master1200.jpg",
        "square_medium": "https://i.pximg.net/c/360x360_70/img-master/img/2018/12/20/00/08/22/72189858_p0_square1200.jpg"
      },
      "is_bookmarked": false,
      "is_muted": false,
      "meta_pages": [],
      "meta_single_page": {
        "original_image_url": "https://i.pximg.net/img-original/img/2018/12/20/00/08/22/72189858_p0.png"
      },
      "page_count": 1,
      "restrict": 0,
      "sanity_level": 2,
      "series": null,
      "tags": [
        {
          "name": "初音ミク",
          "translated_name": null
        },
        {
          "name": "VOCALOID",
          "translated_name": null
        },
        {
          "name": "雪ミク",
          "translated_name": null
        },
        {
          "name": "雪ミク2019",
          "translated_name": null
        },
        {
          "name": "ミクさんマジ天使",
          "translated_name": null
        },
        {
          "name": "VOCALOID5000users入り",
          "translated_name": null
        }
      ],
      "title": "SNOW MIKU 2019",
      "tools": [
        "SAI",
        "Photoshop"
      ],
      "total_bookmarks": 5100,
      "total_view": 19406,
      "type": "illust",
      "user": {
        "account": "sbk951121",
        "id": 2536095,
        "is_followed": false,
        "name": "シナ",
        "profile_image_urls": {
          "medium": "https://i.pximg.net/user-profile/img/2018/12/13/03/21/35/15124821_29b490ed612c7f8f184d19ac1b25bcdd_170.jpg"
        }
      },
      "visible": true,
      "width": 650,
      "x_restrict": 0
    },
    {
      "caption": "",
      "create_date": "2019-01-03T17:13:13+09:00",
      "height": 1136,
      "id": 72472254,
      "image_urls": {
        "large": "https://i.pximg.net/c/600x1200_90/img-master/img/2019/01/03/17/13/13/72472254_p0_master1200.jpg",
        "medium": "https://i.pximg.net/c/540x540_70/img-master/img/2019/01/03/17/13/13/72472254_p0_master1200.jpg",
        "square_medium": "https://i.pximg.net/c/360x360_70/img-master/img/2019/01/03/17/13/13/72472254_p0_square1200.jpg"
      },
      "is_bookmarked": false,
      "is_muted": false,
      "meta_pages": [],
      "meta_single_page": {
        "original_image_url": "https://i.pximg.net/img-original/img/2019/01/03/17/13/13/72472254_p0.jpg"
      },
      "page_count": 1,
      "restrict": 0,
      "sanity_level": 2,
      "series": null,
      "tags": [
        {
          "name": "VOCALOID",
          "translated_name": null
        },
        {
          "name": "初音ミク",
          "translated_name": null
        },
        {
          "name": "雪ミク2019",
          "translated_name": null
        },
        {
          "name": "雪ミク",
          "translated_name": null
        },
        {
          "name": "VOCALOID1000users入り",
          "translated_name": null
        }
      ],
      "title": "雪ミク2019",
      "tools": [
        "Photoshop",
        "CLIP STUDIO PAINT"
      ],
      "total_bookmarks": 2945,
      "total_view": 13157,
      "type": "illust",
      "user": {
        "account": "shadowsinking",
        "id": 777076,
        "is_followed": false,
        "name": "猫小渣@お仕事募集",
        "profile_image_urls": {
          "medium": "https://i.pximg.net/user-profile/img/2011/03/09/17/25/18/2845547_88ebe874b6d841ab744d2c29cd13d62f_170.jpg"
        }
      },
      "visible": true,
      "width": 806,
      "x_restrict": 0
    },
    {
      "caption": "遅れたが、ミク誕生日おめでとう!!",
      "create_date": "2018-09-10T01:29:08+09:00",
      "height": 973,
      "id": 70626212,
      "image_urls": {
        "large": "https://i.pximg.net/c/600x1200_90/img-master/img/2018/09/10/01/29/08/70626212_p0_master1200.jpg",
        "medium": "https://i.pximg.net/c/540x540_70/img-master/img/2018/09/10/01/29/08/70626212_p0_master1200.jpg",
        "square_medium": "https://i.pximg.net/c/360x360_70/img-master/img/2018/09/10/01/29/08/70626212_p0_square1200.jpg"
      },
      "is_bookmarked": false,
      "is_muted": false,
      "meta_pages": [
        {
          "image_urls": {
            "large": "https://i.pximg.net/c/600x1200_90/img-master/img/2018/09/10/01/29/08/70626212_p0_master1200.jpg",
            "medium": "https://i.pximg.net/c/540x540_70/img-master/img/2018/09/10/01/29/08/70626212_p0_master1200.jpg",
            "original": "https://i.pximg.net/img-original/img/2018/09/10/01/29/08/70626212_p0.jpg",
            "square_medium": "https://i.pximg.net/c/360x360_70/img-master/img/2018/09/10/01/29/08/70626212_p0_square1200.jpg"
          }
        },
        {
          "image_urls": {
            "large": "https://i.pximg.net/c/600x1200_90/img-master/img/2018/09/10/01/29/08/70626212_p1_master1200.jpg",
            "medium": "https://i.pximg.net/c/540x540_70/img-master/img/2018/09/10/01/29/08/70626212_p1_master1200.jpg",
            "original": "https://i.pximg.net/img-original/img/2018/09/10/01/29/08/70626212_p1.jpg",
            "square_medium": "https://i.pximg.net/c/360x360_70/img-master/img/2018/09/10/01/29/08/70626212_p1_square1200.jpg"
          }
        }
      ],
      "meta_single_page": {},
      "page_count": 2,
      "restrict": 0,
      "sanity_level": 2,
      "series": null,
      "tags": [
        {
          "name": "初音ミク",
          "translated_name": null
        },
        {
          "name": "VOCALOID",
          "translated_name": null
        },
        {
          "name": "雪ミク2019",
          "translated_name": null
        },
        {
          "name": "雪ミク",
          "translated_name": null
        },
        {
          "name": "ラビット・ユキネ",
          "translated_name": null
        },
        {
          "name": "初音ミク生誕祭2018",
          "translated_name": null
        },
        {
          "name": "VOCALOID5000users入り",
          "translated_name": null
        }
      ],
      "title": "Snow White",
      "tools": [
        "CLIP STUDIO PAINT"
      ],
      "total_bookmarks": 7920,
      "total_view": 48192,
      "type": "illust",
      "user": {
        "account": "dr_poapo",
        "id": 12929463,
        "is_followed": false,
        "name": "popuru/ ポプル",
        "profile_image_urls": {
          "medium": "https://i.pximg.net/user-profile/img/2019/05/01/18/47/51/15713645_0a7425e3824274515e1c4e21419b9fdb_170.jpg"
        }
      },
      "visible": true,
      "width": 1500,
      "x_restrict": 0
    },
    {
      "caption": "今年のミクの日も雪ミクさん<br /><br />Twitter：<strong><a href=\"https://twitter.com/korokoroudon\" target=\"_blank\">twitter/korokoroudon</a></strong>",
      "create_date": "2019-03-10T00:00:02+09:00",
      "height": 1191,
      "id": 73597948,
      "image_urls": {
        "large": "https://i.pximg.net/c/600x1200_90/img-master/img/2019/03/10/00/10/09/73597948_p0_master1200.jpg",
        "medium": "https://i.pximg.net/c/540x540_70/img-master/img/2019/03/10/00/10/09/73597948_p0_master1200.jpg",
        "square_medium": "https://i.pximg.net/c/360x360_70/img-master/img/2019/03/10/00/10/09/73597948_p0_square1200.jpg"
      },
      "is_bookmarked": false,
      "is_muted": false,
      "meta_pages": [
        {
          "image_urls": {
            "large": "https://i.pximg.net/c/600x1200_90/img-master/img/2019/03/10/00/10/09/73597948_p0_master1200.jpg",
            "medium": "https://i.pximg.net/c/540x540_70/img-master/img/2019/03/10/00/10/09/73597948_p0_master1200.jpg",
            "original": "https://i.pximg.net/img-original/img/2019/03/10/00/10/09/73597948_p0.jpg",
            "square_medium": "https://i.pximg.net/c/360x360_70/img-master/img/2019/03/10/00/10/09/73597948_p0_square1200.jpg"
          }
        },
        {
          "image_urls": {
            "large": "https://i.pximg.net/c/600x1200_90/img-master/img/2019/03/10/00/10/09/73597948_p1_master1200.jpg",
            "medium": "https://i.pximg.net/c/540x540_70/img-master/img/2019/03/10/00/10/09/73597948_p1_master1200.jpg",
            "original": "https://i.pximg.net/img-original/img/2019/03/10/00/10/09/73597948_p1.jpg",
            "square_medium": "https://i.pximg.net/c/360x360_70/img-master/img/2019/03/10/00/10/09/73597948_p1_square1200.jpg"
          }
        }
      ],
      "meta_single_page": {},
      "page_count": 2,
      "restrict": 0,
      "sanity_level": 2,
      "series": null,
      "tags": [
        {
          "name": "VOCALOID",
          "translated_name": null
        },
        {
          "name": "初音ミク",
          "translated_name": null
        },
        {
          "name": "雪ミク2019",
          "translated_name": null
        },
        {
          "name": "ミクの日",
          "translated_name": null
        },
        {
          "name": "ミクの日2019",
          "translated_name": null
        },
        {
          "name": "VOCALOID1000users入り",
          "translated_name": null
        }
      ],
      "title": "ミクさんの日",
      "tools": [
        "Photoshop"
      ],
      "total_bookmarks": 3336,
      "total_view": 20589,
      "type": "illust",
      "user": {
        "account": "korokoroudon",
        "id": 2458,
        "is_followed": false,
        "name": "ののこ",
        "profile_image_urls": {
          "medium": "https://i.pximg.net/user-profile/img/2019/01/02/10/41/30/15204350_d47b67f2e57df1911d0a1a848e4a2767_170.jpg"
        }
      },
      "visible": true,
      "width": 1000,
      "x_restrict": 0
    },
    {
      "caption": "雪ミクです。とてもかわいいです~ ☺️ <br /><br />■コラボイベント PV <a href=\"https://youtu.be/YO8I8ZRTqwo\" target=\"_blank\">https://youtu.be/YO8I8ZRTqwo</a>",
      "create_date": "2018-01-31T00:00:19+09:00",
      "height": 1500,
      "id": 67041742,
      "image_urls": {
        "large": "https://i.pximg.net/c/600x1200_90/img-master/img/2018/01/31/00/00/19/67041742_p0_master1200.jpg",
        "medium": "https://i.pximg.net/c/540x540_70/img-master/img/2018/01/31/00/00/19/67041742_p0_master1200.jpg",
        "square_medium": "https://i.pximg.net/c/360x360_70/img-master/img/2018/01/31/00/00/19/67041742_p0_square1200.jpg"
      },
      "is_bookmarked": false,
      "is_muted": false,
      "meta_pages": [],
      "meta_single_page": {
        "original_image_url": "https://i.pximg.net/img-original/img/2018/01/31/00/00/19/67041742_p0.jpg"
      },
      "page_count": 1,
      "restrict": 0,
      "sanity_level": 2,
      "series": null,
      "tags": [
        {
          "name": "雪ミク",
          "translated_name": null
        },
        {
          "name": "雪ミク2018",
          "translated_name": null
        },
        {
          "name": "デスチャ",
          "translated_name": null
        },
        {
          "name": "初音ミク",
          "translated_name": null
        },
        {
          "name": "VOCALOID",
          "translated_name": null
        },
        {
          "name": "VOCALOID10000users入り",
          "translated_name": null
        }
      ],
      "title": "雪ミク 2018",
      "tools": [
        "Photoshop",
        "鉛筆"
      ],
      "total_bookmarks": 19213,
      "total_view": 129841,
      "type": "illust",
      "user": {
        "account": "kkuem",
        "id": 45438,
        "is_followed": false,
        "name": "KKUEMㆍクエム",
        "profile_image_urls": {
          "medium": "https://i.pximg.net/user-profile/img/2013/06/06/01/02/29/6332423_404e065e5f4f6ea9e8336812516ac522_170.jpg"
        }
      },
      "visible": true,
      "width": 1401,
      "x_restrict": 0
    },
    {
      "caption": "❄",
      "create_date": "2018-12-26T00:07:53+09:00",
      "height": 1039,
      "id": 72300854,
      "image_urls": {
        "large": "https://i.pximg.net/c/600x1200_90/img-master/img/2018/12/26/00/07/53/72300854_p0_master1200.jpg",
        "medium": "https://i.pximg.net/c/540x540_70/img-master/img/2018/12/26/00/07/53/72300854_p0_master1200.jpg",
        "square_medium": "https://i.pximg.net/c/360x360_70/img-master/img/2018/12/26/00/07/53/72300854_p0_square1200.jpg"
      },
      "is_bookmarked": false,
      "is_muted": false,
      "meta_pages": [],
      "meta_single_page": {
        "original_image_url": "https://i.pximg.net/img-original/img/2018/12/26/00/07/53/72300854_p0.jpg"
      },
      "page_count": 1,
      "restrict": 0,
      "sanity_level": 2,
      "series": null,
      "tags": [
        {
          "name": "VOCALOID",
          "translated_name": null
        },
        {
          "name": "雪ミク",
          "translated_name": null
        },
        {
          "name": "雪ミク2019",
          "translated_name": null
        },
        {
          "name": "初音ミク",
          "translated_name": null
        },
        {
          "name": "VOCALOID1000users入り",
          "translated_name": null
        }
      ],
      "title": "SNOW MIKU 2019",
      "tools": [
        "SAI",
        "Photoshop"
      ],
      "total_bookmarks": 4286,
      "total_view": 21674,
      "type": "illust",
      "user": {
        "account": "mauve1213",
        "id": 564736,
        "is_followed": false,
        "name": "Mauve",
        "profile_image_urls": {
          "medium": "https://i.pximg.net/user-profile/img/2017/02/24/15/00/26/12190425_06d43a51983bf146d947a39dbb4f7154_170.jpg"
        }
      },
      "visible": true,
      "width": 800,
      "x_restrict": 0
    },
    {
      "caption": "プリンセスっぽく、キラキラと雪の結晶を散りばめてみました！",
      "create_date": "2018-12-30T22:31:50+09:00",
      "height": 1771,
      "id": 72388224,
      "image_urls": {
        "large": "https://i.pximg.net/c/600x1200_90/img-master/img/2018/12/30/22/31/50/72388224_p0_master1200.jpg",
        "medium": "https://i.pximg.net/c/540x540_70/img-master/img/2018/12/30/22/31/50/72388224_p0_master1200.jpg",
        "square_medium": "https://i.pximg.net/c/360x360_70/img-master/img/2018/12/30/22/31/50/72388224_p0_square1200.jpg"
      },
      "is_bookmarked": false,
      "is_muted": false,
      "meta_pages": [],
      "meta_single_page": {
        "original_image_url": "https://i.pximg.net/img-original/img/2018/12/30/22/31/50/72388224_p0.jpg"
      },
      "page_count": 1,
      "restrict": 0,
      "sanity_level": 2,
      "series": null,
      "tags": [
        {
          "name": "VOCALOID",
          "translated_name": null
        },
        {
          "name": "初音ミク",
          "translated_name": null
        },
        {
          "name": "雪ミク",
          "translated_name": null
        },
        {
          "name": "雪ミク2019",
          "translated_name": null
        },
        {
          "name": "ボーカロイド",
          "translated_name": null
        },
        {
          "name": "雪の結晶",
          "translated_name": null
        },
        {
          "name": "VOCALOID1000users入り",
          "translated_name": null
        }
      ],
      "title": "雪ミク2019ちゃん❄️",
      "tools": [],
      "total_bookmarks": 1954,
      "total_view": 6809,
      "type": "illust",
      "user": {
        "account": "user_suxv7437",
        "id": 25490323,
        "is_followed": false,
        "name": "さくらりお",
        "profile_image_urls": {
          "medium": "https://i.pximg.net/user-profile/img/2018/08/04/22/38/48/14583530_9ebf00140e00dbac37b208742aaca6b8_170.jpg"
        }
      },
      "visible": true,
      "width": 1254,
      "x_restrict": 0
    },
    {
      "caption": "素敵な楽曲にイラストを描かせて頂きました♪<br />Youtube/ <a href=\"https://youtu.be/tgJPyLc-zAU\" target=\"_blank\">https://youtu.be/tgJPyLc-zAU</a><br />niconico/ <a href=\"https://www.nicovideo.jp/watch/sm34591293\" target=\"_blank\">https://www.nicovideo.jp/watch/sm34591293</a>",
      "create_date": "2019-02-07T21:35:40+09:00",
      "height": 1004,
      "id": 73055089,
      "image_urls": {
        "large": "https://i.pximg.net/c/600x1200_90/img-master/img/2019/02/07/21/35/40/73055089_p0_master1200.jpg",
        "medium": "https://i.pximg.net/c/540x540_70/img-master/img/2019/02/07/21/35/40/73055089_p0_master1200.jpg",
        "square_medium": "https://i.pximg.net/c/360x360_70/img-master/img/2019/02/07/21/35/40/73055089_p0_square1200.jpg"
      },
      "is_bookmarked": false,
      "is_muted": false,
      "meta_pages": [],
      "meta_single_page": {
        "original_image_url": "https://i.pximg.net/img-original/img/2019/02/07/21/35/40/73055089_p0.png"
      },
      "page_count": 1,
      "restrict": 0,
      "sanity_level": 2,
      "series": null,
      "tags": [
        {
          "name": "初音ミク",
          "translated_name": null
        },
        {
          "name": "VOCALOID",
          "translated_name": null
        },
        {
          "name": "雪ミク",
          "translated_name": null
        },
        {
          "name": "雪ミク2019",
          "translated_name": null
        },
        {
          "name": "ラビット・ユキネ",
          "translated_name": null
        },
        {
          "name": "VOCALOID1000users入り",
          "translated_name": null
        }
      ],
      "title": "Happy!! Snow World!!",
      "tools": [],
      "total_bookmarks": 1281,
      "total_view": 6169,
      "type": "illust",
      "user": {
        "account": "agonasubi_m01",
        "id": 5718940,
        "is_followed": false,
        "name": "あごなすび",
        "profile_image_urls": {
          "medium": "https://i.pximg.net/user-profile/img/2019/03/07/22/56/13/15493132_fd3ada54154aa534d2d0fef0f5d2667f_170.jpg"
        }
      },
      "visible": true,
      "width": 1783,
      "x_restrict": 0
    },
    {
      "caption": "❄「SNOW MIKU 2019」アニメイトオンリーショップのイラストを描かせてもらいました❄<br /><a href=\"https://snowmiku.com/2019/collabo_campaign.html\" target=\"_blank\">https://snowmiku.com/2019/collabo_campaign.html</a>",
      "create_date": "2019-01-22T00:00:04+09:00",
      "height": 778,
      "id": 72780180,
      "image_urls": {
        "large": "https://i.pximg.net/c/600x1200_90/img-master/img/2019/01/22/00/00/04/72780180_p0_master1200.jpg",
        "medium": "https://i.pximg.net/c/540x540_70/img-master/img/2019/01/22/00/00/04/72780180_p0_master1200.jpg",
        "square_medium": "https://i.pximg.net/c/360x360_70/img-master/img/2019/01/22/00/00/04/72780180_p0_square1200.jpg"
      },
      "is_bookmarked": false,
      "is_muted": false,
      "meta_pages": [],
      "meta_single_page": {
        "original_image_url": "https://i.pximg.net/img-original/img/2019/01/22/00/00/04/72780180_p0.jpg"
      },
      "page_count": 1,
      "restrict": 0,
      "sanity_level": 2,
      "series": null,
      "tags": [
        {
          "name": "初音ミク",
          "translated_name": null
        },
        {
          "name": "VOCALOID",
          "translated_name": null
        },
        {
          "name": "雪ミク",
          "translated_name": null
        },
        {
          "name": "雪ミク2019",
          "translated_name": null
        },
        {
          "name": "VOCALOID1000users入り",
          "translated_name": null
        },
        {
          "name": "クリプトン6兄弟",
          "translated_name": null
        },
        {
          "name": "鏡音リン・レン",
          "translated_name": null
        },
        {
          "name": "巡音ルカ",
          "translated_name": null
        },
        {
          "name": "MEIKO",
          "translated_name": null
        },
        {
          "name": "KAITO",
          "translated_name": null
        }
      ],
      "title": "･ﾟ❆。ﾟ。❄ﾟ・",
      "tools": [],
      "total_bookmarks": 4934,
      "total_view": 48824,
      "type": "illust",
      "user": {
        "account": "tiahszld",
        "id": 1589657,
        "is_followed": false,
        "name": "hakusai",
        "profile_image_urls": {
          "medium": "https://i.pximg.net/user-profile/img/2012/09/09/13/06/05/5127538_cad7e119d963b6d0fcfee0cbb7637984_170.jpg"
        }
      },
      "visible": true,
      "width": 1100,
      "x_restrict": 0
    },
    {
      "caption": "",
      "create_date": "2018-12-18T19:47:03+09:00",
      "height": 822,
      "id": 72171832,
      "image_urls": {
        "large": "https://i.pximg.net/c/600x1200_90/img-master/img/2018/12/18/23/07/02/72171832_p0_master1200.jpg",
        "medium": "https://i.pximg.net/c/540x540_70/img-master/img/2018/12/18/23/07/02/72171832_p0_master1200.jpg",
        "square_medium": "https://i.pximg.net/c/360x360_70/img-master/img/2018/12/18/23/07/02/72171832_p0_square1200.jpg"
      },
      "is_bookmarked": false,
      "is_muted": false,
      "meta_pages": [],
      "meta_single_page": {
        "original_image_url": "https://i.pximg.net/img-original/img/2018/12/18/23/07/02/72171832_p0.png"
      },
      "page_count": 1,
      "restrict": 0,
      "sanity_level": 2,
      "series": null,
      "tags": [
        {
          "name": "VOCALOID",
          "translated_name": null
        },
        {
          "name": "初音ミク",
          "translated_name": null
        },
        {
          "name": "雪ミク",
          "translated_name": null
        },
        {
          "name": "雪ミク2019",
          "translated_name": null
        },
        {
          "name": "VOCALOID1000users入り",
          "translated_name": null
        }
      ],
      "title": "雪ミク",
      "tools": [],
      "total_bookmarks": 1894,
      "total_view": 7430,
      "type": "illust",
      "user": {
        "account": "21230641",
        "id": 21230641,
        "is_followed": false,
        "name": "Melings",
        "profile_image_urls": {
          "medium": "https://i.pximg.net/user-profile/img/2018/03/02/01/37/00/13897681_7a8a614d74dd506d8e602188579769c1_170.png"
        }
      },
      "visible": true,
      "width": 1200,
      "x_restrict": 0
    },
    {
      "caption": "今回のSNOW MIKU2019候補作2度(-LF-さん)デザインを描いてみました!<br />原本デザインのリンクはこちらを参考にしてください!<br /><br />-LF-さんの piapro: <a href=\"http://piapro.jp/t/70Dn\" target=\"_blank\">http://piapro.jp/t/70Dn</a><br />-LF-さんの pixiv: <strong><a href=\"pixiv://illusts/68003022\">illust/68003022</a></strong>",
      "create_date": "2018-06-07T18:36:40+09:00",
      "height": 694,
      "id": 69116807,
      "image_urls": {
        "large": "https://i.pximg.net/c/600x1200_90/img-master/img/2018/06/07/18/36/40/69116807_p0_master1200.jpg",
        "medium": "https://i.pximg.net/c/540x540_70/img-master/img/2018/06/07/18/36/40/69116807_p0_master1200.jpg",
        "square_medium": "https://i.pximg.net/c/360x360_70/img-master/img/2018/06/07/18/36/40/69116807_p0_square1200.jpg"
      },
      "is_bookmarked": false,
      "is_muted": false,
      "meta_pages": [],
      "meta_single_page": {
        "original_image_url": "https://i.pximg.net/img-original/img/2018/06/07/18/36/40/69116807_p0.jpg"
      },
      "page_count": 1,
      "restrict": 0,
      "sanity_level": 2,
      "series": null,
      "tags": [
        {
          "name": "女の子",
          "translated_name": null
        },
        {
          "name": "初音ミク",
          "translated_name": null
        },
        {
          "name": "少女",
          "translated_name": null
        },
        {
          "name": "VOCALOID",
          "translated_name": null
        },
        {
          "name": "2019年雪ミク衣装",
          "translated_name": null
        },
        {
          "name": "雪ミク",
          "translated_name": null
        },
        {
          "name": "ラビット・ユキネ",
          "translated_name": null
        },
        {
          "name": "雪ミク2019",
          "translated_name": null
        },
        {
          "name": "VOCALOID5000users入り",
          "translated_name": null
        }
      ],
      "title": "SNOW MIKUさんの村へようこそ!",
      "tools": [
        "CLIP STUDIO PAINT"
      ],
      "total_bookmarks": 6630,
      "total_view": 33962,
      "type": "illust",
      "user": {
        "account": "dr_poapo",
        "id": 12929463,
        "is_followed": false,
        "name": "popuru/ ポプル",
        "profile_image_urls": {
          "medium": "https://i.pximg.net/user-profile/img/2019/05/01/18/47/51/15713645_0a7425e3824274515e1c4e21419b9fdb_170.jpg"
        }
      },
      "visible": true,
      "width": 1000,
      "x_restrict": 0
    },
    {
      "caption": "ライブ行ってきた！記念らくがきです！",
      "create_date": "2019-02-14T00:00:10+09:00",
      "height": 1200,
      "id": 73164939,
      "image_urls": {
        "large": "https://i.pximg.net/c/600x1200_90/img-master/img/2019/02/14/00/00/10/73164939_p0_master1200.jpg",
        "medium": "https://i.pximg.net/c/540x540_70/img-master/img/2019/02/14/00/00/10/73164939_p0_master1200.jpg",
        "square_medium": "https://i.pximg.net/c/360x360_70/img-master/img/2019/02/14/00/00/10/73164939_p0_square1200.jpg"
      },
      "is_bookmarked": false,
      "is_muted": false,
      "meta_pages": [],
      "meta_single_page": {
        "original_image_url": "https://i.pximg.net/img-original/img/2019/02/14/00/00/10/73164939_p0.png"
      },
      "page_count": 1,
      "restrict": 0,
      "sanity_level": 2,
      "series": null,
      "tags": [
        {
          "name": "初音ミク",
          "translated_name": null
        },
        {
          "name": "雪ミク",
          "translated_name": null
        },
        {
          "name": "VOCALOID",
          "translated_name": null
        },
        {
          "name": "ロリ",
          "translated_name": null
        },
        {
          "name": "雪ミク2019",
          "translated_name": null
        },
        {
          "name": "VOCALOID1000users入り",
          "translated_name": null
        }
      ],
      "title": "雪ミク2019",
      "tools": [
        "SAI",
        "Photoshop"
      ],
      "total_bookmarks": 2249,
      "total_view": 13335,
      "type": "illust",
      "user": {
        "account": "poet0210",
        "id": 149587,
        "is_followed": false,
        "name": "永山ゆうのん",
        "profile_image_urls": {
          "medium": "https://i.pximg.net/user-profile/img/2017/10/10/00/43/41/13326043_9a9b83410a7164fc61ca649ab48cda8a_170.png"
        }
      },
      "visible": true,
      "width": 849,
      "x_restrict": 0
    },
    {
      "caption": "コミケの新刊の予約開始いたしました。<br />会場に来れない方は是非ご利用くださいませ！<br /><br />【新刊】<br />アニメイトさん⇒<a href=\"https://www.animate-onlineshop.jp/pn/%E3%80%90%E5%90%8C%E4%BA%BA%E8%AA%8C%E3%80%91eighth%E3%80%80Music/pd/1604146/\" target=\"_blank\">https://www.animate-onlineshop.jp/pn/%E3%80%90%E5%90%8C%E4%BA%BA%E8%AA%8C%E3%80%91eighth%E3%80%80Music/pd/1604146/</a><br /><br />メロンさん⇒<a href=\"https://www.melonbooks.co.jp/detail/detail.php?product_id=458775\" target=\"_blank\">https://www.melonbooks.co.jp/detail/detail.php?product_id=458775</a><br /><br />とらさん⇒<a href=\"https://ec.toranoana.shop/joshi/ec/item/040030694664/\" target=\"_blank\">https://ec.toranoana.shop/joshi/ec/item/040030694664/</a><br /><br />【カレンダー】<br />メロンさん⇒<a href=\"https://www.melonbooks.co.jp/detail/detail.php?product_id=459067\" target=\"_blank\">https://www.melonbooks.co.jp/detail/detail.php?product_id=459067</a>",
      "create_date": "2018-12-24T00:00:14+09:00",
      "height": 849,
      "id": 72253647,
      "image_urls": {
        "large": "https://i.pximg.net/c/600x1200_90/img-master/img/2018/12/24/00/00/14/72253647_p0_master1200.jpg",
        "medium": "https://i.pximg.net/c/540x540_70/img-master/img/2018/12/24/00/00/14/72253647_p0_master1200.jpg",
        "square_medium": "https://i.pximg.net/c/360x360_70/img-master/img/2018/12/24/00/00/14/72253647_p0_square1200.jpg"
      },
      "is_bookmarked": false,
      "is_muted": false,
      "meta_pages": [],
      "meta_single_page": {
        "original_image_url": "https://i.pximg.net/img-original/img/2018/12/24/00/00/14/72253647_p0.jpg"
      },
      "page_count": 1,
      "restrict": 0,
      "sanity_level": 2,
      "series": null,
      "tags": [
        {
          "name": "VOCALOID",
          "translated_name": null
        },
        {
          "name": "初音ミク",
          "translated_name": null
        },
        {
          "name": "雪ミク",
          "translated_name": null
        },
        {
          "name": "雪ミク2019",
          "translated_name": null
        },
        {
          "name": "VOCALOID5000users入り",
          "translated_name": null
        }
      ],
      "title": "🎄🎄🎄雪ミク2019🎄🎄🎄",
      "tools": [
        "Photoshop"
      ],
      "total_bookmarks": 5948,
      "total_view": 27470,
      "type": "illust",
      "user": {
        "account": "korokoroudon",
        "id": 2458,
        "is_followed": false,
        "name": "ののこ",
        "profile_image_urls": {
          "medium": "https://i.pximg.net/user-profile/img/2019/01/02/10/41/30/15204350_d47b67f2e57df1911d0a1a848e4a2767_170.jpg"
        }
      },
      "visible": true,
      "width": 1200,
      "x_restrict": 0
    },
    {
      "caption": "",
      "create_date": "2018-08-31T00:00:10+09:00",
      "height": 959,
      "id": 70462748,
      "image_urls": {
        "large": "https://i.pximg.net/c/600x1200_90/img-master/img/2018/08/31/00/00/10/70462748_p0_master1200.jpg",
        "medium": "https://i.pximg.net/c/540x540_70/img-master/img/2018/08/31/00/00/10/70462748_p0_master1200.jpg",
        "square_medium": "https://i.pximg.net/c/360x360_70/img-master/img/2018/08/31/00/00/10/70462748_p0_square1200.jpg"
      },
      "is_bookmarked": false,
      "is_muted": false,
      "meta_pages": [],
      "meta_single_page": {
        "original_image_url": "https://i.pximg.net/img-original/img/2018/08/31/00/00/10/70462748_p0.png"
      },
      "page_count": 1,
      "restrict": 0,
      "sanity_level": 2,
      "series": null,
      "tags": [
        {
          "name": "VOCALOID",
          "translated_name": null
        },
        {
          "name": "雪ミク",
          "translated_name": null
        },
        {
          "name": "初音ミク",
          "translated_name": null
        },
        {
          "name": "雪ミク2019",
          "translated_name": null
        },
        {
          "name": "初音ミク生誕祭2018",
          "translated_name": null
        },
        {
          "name": "VOCALOID10000users入り",
          "translated_name": null
        }
      ],
      "title": "氷のプリンセス",
      "tools": [],
      "total_bookmarks": 10243,
      "total_view": 40384,
      "type": "illust",
      "user": {
        "account": "hzc_hyr",
        "id": 1460159,
        "is_followed": false,
        "name": "KANOSE",
        "profile_image_urls": {
          "medium": "https://i.pximg.net/user-profile/img/2016/04/14/01/07/47/10803306_8a26a1f8d561a3427a55ab0a84d1fccc_170.jpg"
        }
      },
      "visible": true,
      "width": 1400,
      "x_restrict": 0
    },
    {
      "caption": "",
      "create_date": "2018-12-12T02:03:27+09:00",
      "height": 5016,
      "id": 72074790,
      "image_urls": {
        "large": "https://i.pximg.net/c/600x1200_90/img-master/img/2018/12/12/02/03/27/72074790_p0_master1200.jpg",
        "medium": "https://i.pximg.net/c/540x540_70/img-master/img/2018/12/12/02/03/27/72074790_p0_master1200.jpg",
        "square_medium": "https://i.pximg.net/c/360x360_70/img-master/img/2018/12/12/02/03/27/72074790_p0_square1200.jpg"
      },
      "is_bookmarked": false,
      "is_muted": false,
      "meta_pages": [],
      "meta_single_page": {
        "original_image_url": "https://i.pximg.net/img-original/img/2018/12/12/02/03/27/72074790_p0.jpg"
      },
      "page_count": 1,
      "restrict": 0,
      "sanity_level": 2,
      "series": null,
      "tags": [
        {
          "name": "VOCALOID",
          "translated_name": null
        },
        {
          "name": "初音ミク",
          "translated_name": null
        },
        {
          "name": "雪ミク",
          "translated_name": null
        },
        {
          "name": "雪ミク2019",
          "translated_name": null
        },
        {
          "name": "VOCALOID1000users入り",
          "translated_name": null
        }
      ],
      "title": "雪ミク2019ちゃん",
      "tools": [],
      "total_bookmarks": 2719,
      "total_view": 11952,
      "type": "illust",
      "user": {
        "account": "eneosu",
        "id": 5599364,
        "is_followed": false,
        "name": "ごろー",
        "profile_image_urls": {
          "medium": "https://i.pximg.net/user-profile/img/2017/07/31/20/06/53/12955530_a92e8f639f908fd89f1d3a7f89ee1b76_170.png"
        }
      },
      "visible": true,
      "width": 3541,
      "x_restrict": 0
    },
    {
      "caption": "2019第一張!",
      "create_date": "2019-01-01T22:03:21+09:00",
      "height": 990,
      "id": 72439808,
      "image_urls": {
        "large": "https://i.pximg.net/c/600x1200_90/img-master/img/2019/01/01/22/03/21/72439808_p0_master1200.jpg",
        "medium": "https://i.pximg.net/c/540x540_70/img-master/img/2019/01/01/22/03/21/72439808_p0_master1200.jpg",
        "square_medium": "https://i.pximg.net/c/360x360_70/img-master/img/2019/01/01/22/03/21/72439808_p0_square1200.jpg"
      },
      "is_bookmarked": false,
      "is_muted": false,
      "meta_pages": [],
      "meta_single_page": {
        "original_image_url": "https://i.pximg.net/img-original/img/2019/01/01/22/03/21/72439808_p0.jpg"
      },
      "page_count": 1,
      "restrict": 0,
      "sanity_level": 2,
      "series": null,
      "tags": [
        {
          "name": "VOCALOID",
          "translated_name": null
        },
        {
          "name": "初音ミク",
          "translated_name": null
        },
        {
          "name": "雪ミク",
          "translated_name": null
        },
        {
          "name": "雪ミク2019",
          "translated_name": null
        },
        {
          "name": "VOCALOID1000users入り",
          "translated_name": null
        }
      ],
      "title": "❄2019❄",
      "tools": [
        "CLIP STUDIO PAINT"
      ],
      "total_bookmarks": 1673,
      "total_view": 9243,
      "type": "illust",
      "user": {
        "account": "sky3326",
        "id": 1135942,
        "is_followed": false,
        "name": "_FEI@仕事募集中",
        "profile_image_urls": {
          "medium": "https://i.pximg.net/user-profile/img/2015/12/01/16/39/02/10189090_43222a4e36e1293511f2fcde94ce74c2_170.jpg"
        }
      },
      "visible": true,
      "width": 700,
      "x_restrict": 0
    }
  ],
  "next_url": "https://app-api.pixiv.net/v2/illust/related?illust_id=73011378&filter=for_ios&seed_illust_ids%5B0%5D=72171832&seed_illust_ids%5B1%5D=67041742&seed_illust_ids%5B2%5D=73164939&seed_illust_ids%5B3%5D=73591526&seed_illust_ids%5B4%5D=72439808&seed_illust_ids%5B5%5D=72086224&seed_illust_ids%5B6%5D=72908044&seed_illust_ids%5B7%5D=65567135&seed_illust_ids%5B8%5D=69116807&seed_illust_ids%5B9%5D=72253647&seed_illust_ids%5B10%5D=70626212&seed_illust_ids%5B11%5D=72218158&seed_illust_ids%5B12%5D=56985812&seed_illust_ids%5B13%5D=73055089&seed_illust_ids%5B14%5D=70462748&seed_illust_ids%5B15%5D=72036945&seed_illust_ids%5B16%5D=73404075&seed_illust_ids%5B17%5D=73597948&seed_illust_ids%5B18%5D=72074790&seed_illust_ids%5B19%5D=72189858"
}